ros2_simple_sub/__init__.py
ros2_simple_sub/subscriber.py
ros2_simple_sub-0.1.0.dist-info/METADATA
ros2_simple_sub-0.1.0.dist-info/WHEEL
ros2_simple_sub-0.1.0.dist-info/top_level.txt
ros2_simple_sub-0.1.0.dist-info/RECORD
