Metadata-Version: 2.4
Name: ros2_simple_sub
Version: 0.1.0
Summary: A simple configurable ROS2 subscriber
Author: Your Name
Author-email: you@example.com
Requires-Python: >=3.7
Dynamic: author
Dynamic: author-email
Dynamic: description
Dynamic: description-content-type
Dynamic: requires-python
Dynamic: summary
